top/IF_IDReg.sv
module IF_IDReg(clk, IF_PC, IF_Instruction, ID_PC, ID_Instruction);
    input wire [11:0] IF_PC;
    input wire [31:0] IF_Instruction;
    output reg [11:0] ID_PC;
    output reg [31:0] ID_Instruction;
    input wire clk;

    reg innerClk; // internal clock for emulate the setup & hold time
    reg [11:0] PC;
    reg [31:0] Instruction;

    always_ff @(posedge innerClk) begin
        PC <= IF_PC;
        Instruction <= IF_Instruction;
    end

    always_ff @(posedge clk) begin
        ID_PC <= PC;
        ID_Instruction <= Instruction;
    end

    initial begin
        innerClk = 0;
        #1;
        forever begin
            #8 innerClk = ~innerClk; // emulate the setup & hold time
            #2 innerClk = ~innerClk; // emulate the setup & hold time
        end
    end



endmodule

tbs/tb_IF_IDReg.sv
`include "./top/IF_IDReg.sv"
module tb_IF_IDReg();

reg clk;
reg [11:0] IF_PC;
reg [31:0] IF_Instruction;
reg [11:0] ID_PC;
reg [31:0] ID_Instruction;

IF_IDReg dut (.IF_PC(IF_PC), .IF_Instruction(IF_Instruction), .ID_PC(ID_PC), .ID_Instruction(ID_Instruction), .clk(clk));

initial begin
    clk = 0;
    forever begin
        clk = ~clk;
        #5;
    end
end

initial begin
    $dumpfile("pv.vcd");
    $dumpvars(0, tb_IF_IDReg);
    IF_PC = 12'h0;
    IF_Instruction = 32'h0;
    #10;
    IF_PC = 12'h4;
    IF_Instruction = 32'h4;
    #10;
    IF_PC = 12'h8;
    IF_Instruction = 32'h8;
    #10;
    IF_PC = 12'hC;
    IF_Instruction = 32'hC;
    #10;
    $finish;
end

endmodule

pv.vcd
$date
	Thu May 30 14:02:35 2024
$end
$version
	Icarus Verilog
$end
$timescale
	1s
$end
$scope module tb_IF_IDReg $end
$var wire 12 ! ID_PC [11:0] $end
$var wire 32 " ID_Instruction [31:0] $end
$var reg 32 # IF_Instruction [31:0] $end
$var reg 12 $ IF_PC [11:0] $end
$var reg 1 % clk $end
$scope module dut $end
$var wire 32 & IF_Instruction [31:0] $end
$var wire 12 ' IF_PC [11:0] $end
$var wire 1 % clk $end
$var reg 32 ( ID_Instruction [31:0] $end
$var reg 12 ) ID_PC [11:0] $end
$var reg 32 * Instruction [31:0] $end
$var reg 12 + PC [11:0] $end
$var reg 1 , innerClk $end
$upscope $end
$upscope $end
$enddefinitions $end
$comment Show the parameter values. $end
$dumpall
$end
#0
$dumpvars
0,
bx +
bx *
bx )
bx (
b0 '
b0 &
1%
b0 $
b0 #
bx "
bx !
$end
#5
0%
#9
b0 *
b0 +
1,
#10
b0 "
b0 (
b0 !
b0 )
1%
b100 #
b100 &
b100 $
b100 '
#11
0,
#15
0%
#19
b100 *
b100 +
1,
#20
b100 "
b100 (
b100 !
b100 )
1%
b1000 #
b1000 &
b1000 $
b1000 '
#21
0,
#25
0%
#29
b1000 *
b1000 +
1,
#30
b1000 "
b1000 (
b1000 !
b1000 )
1%
b1100 #
b1100 &
b1100 $
b1100 '
#31
0,
#35
0%
#39
b1100 *
b1100 +
1,
#40
b1100 "
b1100 (
b1100 !
b1100 )
1%
